{
  "pipeline": "dhamma-video-complete",
  "run_id": "production_20251106_135324",
  "started_at": "2025-11-06T13:53:25.468295",
  "total_steps": 17,
  "successful": 17,
  "failed": 0,
  "results": {
    "trend_scout": {
      "status": "success",
      "output": "D:\\Auto Tool\\dhamma-channel-automation\\output\\production_20251106_135324\\trend_candidates.json"
    },
    "topic_prioritizer": {
      "status": "success",
      "output": "D:\\Auto Tool\\dhamma-channel-automation\\output\\production_20251106_135324\\topics_ranked.json"
    },
    "research_retrieval": {
      "status": "success",
      "output": "D:\\Auto Tool\\dhamma-channel-automation\\output\\production_20251106_135324\\research_bundle.json"
    },
    "data_enrichment": {
      "status": "success",
      "output": "D:\\Auto Tool\\dhamma-channel-automation\\output\\production_20251106_135324\\data_enrichment.json"
    },
    "script_outline": {
      "status": "success",
      "output": "D:\\Auto Tool\\dhamma-channel-automation\\output\\production_20251106_135324\\outline.md"
    },
    "script_writer": {
      "status": "success",
      "output": "D:\\Auto Tool\\dhamma-channel-automation\\output\\production_20251106_135324\\script.md"
    },
    "doctrine_validator": {
      "status": "success",
      "output": "D:\\Auto Tool\\dhamma-channel-automation\\output\\production_20251106_135324\\script_validated.md"
    },
    "legal_compliance": {
      "status": "success",
      "output": "D:\\Auto Tool\\dhamma-channel-automation\\output\\production_20251106_135324\\compliance_report.json"
    },
    "visual_asset": {
      "status": "success",
      "output": "D:\\Auto Tool\\dhamma-channel-automation\\output\\production_20251106_135324\\visual_guide.json"
    },
    "voiceover": {
      "status": "success",
      "output": "D:\\Auto Tool\\dhamma-channel-automation\\output\\production_20251106_135324\\voiceover_guide.json"
    },
    "localization": {
      "status": "success",
      "output": "D:\\Auto Tool\\dhamma-channel-automation\\output\\production_20251106_135324\\localization.json"
    },
    "seo_metadata": {
      "status": "success",
      "output": "D:\\Auto Tool\\dhamma-channel-automation\\output\\production_20251106_135324\\metadata.json"
    },
    "thumbnail_generator": {
      "status": "success",
      "output": "D:\\Auto Tool\\dhamma-channel-automation\\output\\production_20251106_135324\\thumbnail_concepts.json"
    },
    "format_conversion": {
      "status": "success",
      "output": "D:\\Auto Tool\\dhamma-channel-automation\\output\\production_20251106_135324\\format_specs.json"
    },
    "multi_channel": {
      "status": "success",
      "output": "D:\\Auto Tool\\dhamma-channel-automation\\output\\production_20251106_135324\\multi_channel.json"
    },
    "publish": {
      "status": "success",
      "output": "D:\\Auto Tool\\dhamma-channel-automation\\output\\production_20251106_135324\\publish_receipt.json"
    },
    "backup_archive": {
      "status": "success",
      "output": "D:\\Auto Tool\\dhamma-channel-automation\\output\\production_20251106_135324\\backup_manifest.json"
    }
  },
  "output_dir": "D:\\Auto Tool\\dhamma-channel-automation\\output\\production_20251106_135324"
}